setup.cfg
setup.py
libreERP_cli.egg-info/PKG-INFO
libreERP_cli.egg-info/SOURCES.txt
libreERP_cli.egg-info/dependency_links.txt
libreERP_cli.egg-info/entry_points.txt
libreERP_cli.egg-info/not-zip-safe
libreERP_cli.egg-info/requires.txt
libreERP_cli.egg-info/top_level.txt
libreerp/__init__.py
libreerp/cli.py
libreerp/ui.py