Metadata-Version: 1.1
Name: libreERP-cli
Version: 0.1.0
Summary: Command line tools and dev modules for libreERP project.
Home-page: https://github.com/pkyad/libreERP-cli
Author: Pradeep Yadav
Author-email: pkyisky@gmail.com
License: GPL2
Platform: any
Classifier: Development Status :: 4 - Beta
Classifier: Environment :: Console
Classifier: Intended Audience :: Developers
Classifier: License :: OSI Approved :: GNU General Public License v2 (GPLv2)
Classifier: Operating System :: Unix
Classifier: Operating System :: Microsoft
Classifier: Programming Language :: Python
Classifier: Programming Language :: Python :: 2
Classifier: Topic :: Software Development :: Libraries :: Python Modules
